aioredlock/__init__.py
aioredlock/algorithm.py
aioredlock/errors.py
aioredlock/lock.py
aioredlock/redis.py
aioredlock/sentinel.py
aioredlock/utility.py
aioredlock-0.7.3.dist-info/LICENSE.md
aioredlock-0.7.3.dist-info/METADATA
aioredlock-0.7.3.dist-info/WHEEL
aioredlock-0.7.3.dist-info/top_level.txt
aioredlock-0.7.3.dist-info/RECORD
