Metadata-Version: 2.1
Name: aioredlock
Version: 0.7.3
Summary: Asyncio implemetation of Redis distributed locks
Home-page: https://github.com/joanvila/aioredlock
Author: Joan Vilà Cuñat
Author-email: vila.joan94@gmail.com
License: MIT
Keywords: redis redlock distributed locks asyncio
Platform: UNKNOWN
Classifier: Development Status :: 5 - Production/Stable
Classifier: Intended Audience :: Developers
Classifier: Topic :: Software Development :: Libraries :: Python Modules
Classifier: License :: OSI Approved :: MIT License
Classifier: Programming Language :: Python :: 3
Classifier: Programming Language :: Python :: 3.7
Classifier: Programming Language :: Python :: 3.8
Classifier: Programming Language :: Python :: 3.9
Requires-Python: >=3.6
Provides-Extra: test
Provides-Extra: cicd
Provides-Extra: package
Provides-Extra: examples
